gemini_cli_bridge.py
gemini_cli_bridge-0.1.2.dist-info/METADATA
gemini_cli_bridge-0.1.2.dist-info/WHEEL
gemini_cli_bridge-0.1.2.dist-info/entry_points.txt
gemini_cli_bridge-0.1.2.dist-info/licenses/LICENSE
gemini_cli_bridge-0.1.2.dist-info/RECORD
