Metadata-Version: 2.4
Name: gemini-cli-bridge
Version: 0.1.2
Summary: MCP bridge for Gemini CLI and handy system/web tools
Author: Your Name
License: MIT
License-File: LICENSE
Keywords: CLI,Gemini,MCP,bridge
Requires-Python: >=3.10
Requires-Dist: duckduckgo-search>=6.1.0
Requires-Dist: fastmcp>=0.3.0
Requires-Dist: requests>=2.31.0
